wagtail_modeltranslation/__init__.py
wagtail_modeltranslation/apps.py
wagtail_modeltranslation/contextlib.py
wagtail_modeltranslation/makemigrations/__init__.py
wagtail_modeltranslation/makemigrations/apps.py
wagtail_modeltranslation/makemigrations/management/__init__.py
wagtail_modeltranslation/makemigrations/management/commands/__init__.py
wagtail_modeltranslation/makemigrations/management/commands/makemigrations.py
wagtail_modeltranslation/makemigrations/management/commands/makemigrations_original.py
wagtail_modeltranslation/management/__init__.py
wagtail_modeltranslation/management/commands/__init__.py
wagtail_modeltranslation/management/commands/makemigrations_translation.py
wagtail_modeltranslation/management/commands/migrate_translation.py
wagtail_modeltranslation/management/commands/set_translation_url_paths.py
wagtail_modeltranslation/management/commands/sync_page_translation_fields.py
wagtail_modeltranslation/management/commands/update_translation_fields.py
wagtail_modeltranslation/migrate/__init__.py
wagtail_modeltranslation/migrate/apps.py
wagtail_modeltranslation/migrate/management/__init__.py
wagtail_modeltranslation/migrate/management/commands/__init__.py
wagtail_modeltranslation/migrate/management/commands/migrate.py
wagtail_modeltranslation/migrate/management/commands/migrate_original.py
wagtail_modeltranslation/patch_wagtailadmin.py
wagtail_modeltranslation/patch_wagtailadmin_forms.py
wagtail_modeltranslation/settings.py
wagtail_modeltranslation/signal_handlers.py
wagtail_modeltranslation/static/wagtail_modeltranslation/css/admin_patch.css
wagtail_modeltranslation/static/wagtail_modeltranslation/css/language_toggles.css
wagtail_modeltranslation/static/wagtail_modeltranslation/css/page_editor_modeltranslation.css
wagtail_modeltranslation/static/wagtail_modeltranslation/js/copy_stream_fields.js
wagtail_modeltranslation/static/wagtail_modeltranslation/js/force_jquery.js
wagtail_modeltranslation/static/wagtail_modeltranslation/js/js.cookie.js
wagtail_modeltranslation-0.16.0.dist-info/METADATA
wagtail_modeltranslation-0.16.0.dist-info/WHEEL
wagtail_modeltranslation-0.16.0.dist-info/licenses/AUTHORS.rst
wagtail_modeltranslation-0.16.0.dist-info/RECORD
