Metadata-Version: 2.4
Name: wagtail-modeltranslation
Version: 0.16.0
Summary: Translates Wagtail CMS models using a registration approach.
License: New BSD
License-File: AUTHORS.rst
Keywords: django,wagtail,translation,i18n
Author: InfoPortugal S.A.
Author-email: suporte24@infoportugal.pt
Maintainer: InfoPortugal S.A.
Maintainer-email: suporte24@infoportugal.pt
Requires-Python: >=3.9,<4.0
Classifier: Environment :: Web Environment
Classifier: Framework :: Django
Classifier: Intended Audience :: Developers
Classifier: License :: OSI Approved :: BSD License
Classifier: License :: Other/Proprietary License
Classifier: Operating System :: OS Independent
Classifier: Programming Language :: Python :: 3
Classifier: Programming Language :: Python :: 3.9
Classifier: Programming Language :: Python :: 3.10
Classifier: Programming Language :: Python :: 3.11
Classifier: Programming Language :: Python :: 3.12
Classifier: Programming Language :: Python :: 3.13
Classifier: Programming Language :: Python :: 3.14
Requires-Dist: Django (>=4.2)
Requires-Dist: django-modeltranslation (>=0.19)
Requires-Dist: wagtail (>=6.4,<8)
Project-URL: Repository, https://github.com/infoportugal/wagtail-modeltranslation
